.travis.yml
MANIFEST.in
README.txt
bootstrap.py
buildout.cfg
setup.cfg
setup.py
test.cfg
docs/HISTORY.txt
docs/INSTALL.txt
docs/LICENSE.GPL
docs/LICENSE.txt
quintagroup/__init__.py
quintagroup.plonecomments.egg-info/PKG-INFO
quintagroup.plonecomments.egg-info/SOURCES.txt
quintagroup.plonecomments.egg-info/dependency_links.txt
quintagroup.plonecomments.egg-info/entry_points.txt
quintagroup.plonecomments.egg-info/namespace_packages.txt
quintagroup.plonecomments.egg-info/not-zip-safe
quintagroup.plonecomments.egg-info/requires.txt
quintagroup.plonecomments.egg-info/top_level.txt
quintagroup/plonecomments/__init__.py
quintagroup/plonecomments/config.py
quintagroup/plonecomments/configure.zcml
quintagroup/plonecomments/interfaces.py
quintagroup/plonecomments/overrides.zcml
quintagroup/plonecomments/patch.py
quintagroup/plonecomments/profiles.zcml
quintagroup/plonecomments/setuphandlers.py
quintagroup/plonecomments/skins.zcml
quintagroup/plonecomments/upgrades.py
quintagroup/plonecomments/utils.py
quintagroup/plonecomments/Extensions/Install.py
quintagroup/plonecomments/browser/__init__.py
quintagroup/plonecomments/browser/comments.pt
quintagroup/plonecomments/browser/comments.py
quintagroup/plonecomments/browser/configure.zcml
quintagroup/plonecomments/locales/quintagroup.plonecomments.pot
quintagroup/plonecomments/locales/de/LC_MESSAGES/quintagroup.plonecomments.po
quintagroup/plonecomments/locales/es/LC_MESSAGES/quintagroup.plonecomments.po
quintagroup/plonecomments/locales/fr/LC_MESSAGES/quintagroup.plonecomments.po
quintagroup/plonecomments/locales/it/LC_MESSAGES/quintagroup.plonecomments.po
quintagroup/plonecomments/locales/nl/LC_MESSAGES/quintagroup.plonecomments.po
quintagroup/plonecomments/locales/pt-br/LC_MESSAGES/quintagroup.plonecomments.po
quintagroup/plonecomments/locales/ro/LC_MESSAGES/quintagroup.plonecomments.po
quintagroup/plonecomments/locales/uk/LC_MESSAGES/quintagroup.plonecomments.po
quintagroup/plonecomments/profiles/default/actionicons.xml
quintagroup/plonecomments/profiles/default/browserlayer.xml
quintagroup/plonecomments/profiles/default/controlpanel.xml
quintagroup/plonecomments/profiles/default/cssregistry.xml
quintagroup/plonecomments/profiles/default/jsregistry.xml
quintagroup/plonecomments/profiles/default/kssregistry.xml
quintagroup/plonecomments/profiles/default/metadata.xml
