Metadata-Version: 1.0
Name: quintagroup.plonecomments
Version: 4.1.9
Summary: Plone Comments
Home-page: http://quintagroup.com/services/plone-development/products/plone-comments
Author: Quintagroup
Author-email: support@quintagroup.com
License: GPL
Keywords: web zope plone comments discussion
Platform: UNKNOWN
Classifier: Framework :: Plone
Classifier: Framework :: Plone :: 3.2
Classifier: Framework :: Plone :: 3.3
Classifier: Framework :: Plone :: 4.0
Classifier: Framework :: Zope2
Classifier: Framework :: Zope3
Classifier: Programming Language :: Python
Classifier: Topic :: Software Development :: Libraries :: Python Modules
Classifier: License :: OSI Approved :: GNU General Public License (GPL)
Classifier: Operating System :: OS Independent
Classifier: Development Status :: 5 - Production/Stable
